unillm/README.md
unillm/__init__.py
unillm/anthropic.py
unillm/client.py
unillm/client_models.py
unillm/exceptions.py
unillm/models.py
unillm/openai.py
unillm/registry.py
unillm/test_dropin_vs_native.py
unillm/test_openai_dropin.py
unillm/test_unillm_examples.py
unillm/adapters/__init__.py
unillm/adapters/anthropic_adapter.py
unillm/adapters/base.py
unillm/adapters/cohere_adapter.py
unillm/adapters/gemini_adapter.py
unillm/adapters/mistral_adapter.py
unillm/adapters/openai_adapter.py
unifyllm_sdk-0.1.3.dist-info/METADATA
unifyllm_sdk-0.1.3.dist-info/WHEEL
unifyllm_sdk-0.1.3.dist-info/top_level.txt
unifyllm_sdk-0.1.3.dist-info/RECORD
