Metadata-Version: 2.4
Name: unifyllm-sdk
Version: 0.1.3
Summary: Unified Python client for multiple LLM providers (OpenAI, Anthropic, etc.) with drop-in compatibility.
Home-page: https://github.com/sahilhd/unifyllm-sdk
Author: Sahil Handa
Author-email: Sahil Handa <sahilhandauni@gmail.com>
Project-URL: Homepage, https://github.com/unillm/unillm-python
Project-URL: Repository, https://github.com/unillm/unillm-python
Project-URL: Documentation, https://docs.unillm.com
Requires-Python: >=3.7
Requires-Dist: requests>=2.28.0
Requires-Dist: pydantic>=2.0.0
Provides-Extra: dev
Requires-Dist: pytest>=7.0.0; extra == "dev"
Requires-Dist: pytest-cov>=4.0.0; extra == "dev"
Requires-Dist: black>=23.0.0; extra == "dev"
Requires-Dist: isort>=5.0.0; extra == "dev"
Requires-Dist: mypy>=1.0.0; extra == "dev"
Requires-Dist: flake8>=6.0.0; extra == "dev"
Dynamic: author
Dynamic: home-page
Dynamic: requires-python
